btrack/__init__.py
btrack/_version.py
btrack/btypes.py
btrack/config.py
btrack/constants.py
btrack/core.py
btrack/dataio.py
btrack/datasets.py
btrack/libwrapper.py
btrack/models.py
btrack/napari.yaml
btrack/utils.py
btrack/include/bayes.h
btrack/include/belief.h
btrack/include/defs.h
btrack/include/hyperbin.h
btrack/include/hypothesis.h
btrack/include/inference.h
btrack/include/manager.h
btrack/include/motion.h
btrack/include/pdf.h
btrack/include/tracker.h
btrack/include/tracklet.h
btrack/include/types.h
btrack/include/updates.h
btrack/include/wrapper.h
btrack/io/__init__.py
btrack/io/_localization.py
btrack/io/exporters.py
btrack/io/hdf.py
btrack/io/importers.py
btrack/io/utils.py
btrack/libs/libtracker.DLL
btrack/libs/libtracker.dylib
btrack/libs/libtracker.so
btrack/napari/__init__.py
btrack/napari/config.py
btrack/napari/constants.py
btrack/napari/main.py
btrack/napari/reader.py
btrack/napari/sync.py
btrack/napari/writer.py
btrack/napari/assets/btrack_logo.png
btrack/napari/examples/show_btrack_widget.py
btrack/napari/widgets/__init__.py
btrack/napari/widgets/_general.py
btrack/napari/widgets/_motion.py
btrack/napari/widgets/_optimiser.py
btrack/napari/widgets/create_ui.py
btrack/napari/widgets/io.py
btrack/optimise/__init__.py
btrack/optimise/hypothesis.py
btrack/optimise/optimiser.py
btrack/src/bayes.cc
btrack/src/belief.cu
btrack/src/hyperbin.cc
btrack/src/hypothesis.cc
btrack/src/inference.cc
btrack/src/interface.cc
btrack/src/manager.cc
btrack/src/motion.cc
btrack/src/pdf.cc
btrack/src/tracker.cc
btrack/src/tracklet.cc
btrack/src/wrapper.cc
btrack-0.7.0.dist-info/licenses/LICENSE.md
btrack-0.7.0.dist-info/METADATA
btrack-0.7.0.dist-info/WHEEL
btrack-0.7.0.dist-info/entry_points.txt
btrack-0.7.0.dist-info/top_level.txt
btrack-0.7.0.dist-info/RECORD
