Metadata-Version: 2.4
Name: btrack
Version: 0.7.0
Summary: A framework for Bayesian multi-object tracking
Author-email: "Alan R. Lowe" <a.lowe@ucl.ac.uk>
License: MIT License
Project-URL: bugtracker, https://github.com/quantumjot/btrack/issues
Project-URL: documentation, https://btrack.readthedocs.io
Project-URL: homepage, https://github.com/quantumjot/btrack
Project-URL: usersupport, https://github.com/quantumjot/btrack/discussions
Classifier: Framework :: napari
Classifier: Intended Audience :: Science/Research
Classifier: License :: OSI Approved :: MIT License
Classifier: Operating System :: OS Independent
Classifier: Programming Language :: C++
Classifier: Programming Language :: Python :: 3
Classifier: Programming Language :: Python :: 3 :: Only
Classifier: Programming Language :: Python :: 3.10
Classifier: Programming Language :: Python :: 3.11
Classifier: Programming Language :: Python :: 3.12
Classifier: Programming Language :: Python :: 3.13
Classifier: Topic :: Scientific/Engineering :: Bio-Informatics
Classifier: Topic :: Scientific/Engineering :: Image Recognition
Classifier: Topic :: Scientific/Engineering :: Visualization
Requires-Python: >=3.9
License-File: LICENSE.md
Requires-Dist: cvxopt>=1.3.1
Requires-Dist: h5py>=2.10.0
Requires-Dist: numpy>=1.17.3
Requires-Dist: pandas>=2.0.3
Requires-Dist: pooch>=1.0.0
Requires-Dist: pydantic>=2.0.0
Requires-Dist: scikit-image>=0.16.2
Requires-Dist: scipy>=1.3.1
Requires-Dist: tqdm>=4.65.0
Provides-Extra: dev
Requires-Dist: black; extra == "dev"
Requires-Dist: pre-commit; extra == "dev"
Requires-Dist: ruff; extra == "dev"
Provides-Extra: docs
Requires-Dist: numpydoc; extra == "docs"
Requires-Dist: pytz; extra == "docs"
Requires-Dist: sphinx; extra == "docs"
Requires-Dist: sphinx-automodapi; extra == "docs"
Requires-Dist: sphinx-panels; extra == "docs"
Requires-Dist: sphinx_rtd_theme; extra == "docs"
Provides-Extra: napari
Requires-Dist: magicgui>=0.5.0; extra == "napari"
Requires-Dist: napari-plugin-engine>=0.1.4; extra == "napari"
Requires-Dist: napari>=0.4.16; extra == "napari"
Requires-Dist: qtpy; extra == "napari"
Dynamic: license-file
